isensus/__init__.py
isensus/__main__.py
isensus/version.py
isensus/commands/__init__.py
isensus/commands/commands.py
isensus/commands/create.py
isensus/commands/delnote.py
isensus/commands/delwarning.py
isensus/commands/list.py
isensus/commands/remove.py
isensus/commands/rm.py
isensus/commands/set.py
isensus/commands/show.py
isensus/data/__init__.py
isensus/data/contract.py
isensus/data/data.py
isensus/data/date.py
isensus/data/list_attribute.py
isensus/data/notes.py
isensus/data/title.py
isensus/data/user.py
isensus/data/warnings.py
isensus/defaults/__init__.py
isensus/errors/__init__.py
isensus/errors/ambiguous_user.py
isensus/errors/existing_user.py
isensus/errors/unknown_attribute.py
isensus/errors/user_not_found.py
isensus-0.3b0.dist-info/LICENSE
isensus-0.3b0.dist-info/METADATA
isensus-0.3b0.dist-info/WHEEL
isensus-0.3b0.dist-info/entry_points.txt
isensus-0.3b0.dist-info/top_level.txt
isensus-0.3b0.dist-info/RECORD
