Metadata-Version: 2.1
Name: isensus
Version: 0.3b0
Summary: "Tool for the IT systems admins of the Max Planck Institute for Intelligent System to track the status of their users."
Home-page: UNKNOWN
License: BSD 3-Clause License
Platform: UNKNOWN
Classifier: Programming Language :: Python :: 3.8
Provides-Extra: test
Requires-Dist: pytest ; extra == 'test'
